izk/__init__.py
izk/completion.py
izk/formatting.py
izk/lexer.py
izk/prompt.py
izk/runner.py
izk/utils.py
izk/validation.py
izk/zk.py
izk-0.4.4.dist-info/entry_points.txt
izk-0.4.4.dist-info/LICENSE
izk-0.4.4.dist-info/WHEEL
izk-0.4.4.dist-info/METADATA
izk-0.4.4.dist-info/RECORD
